test_pack_kotek/__init__.py
test_pack_kotek-0.0.1.dist-info/METADATA
test_pack_kotek-0.0.1.dist-info/WHEEL
test_pack_kotek-0.0.1.dist-info/top_level.txt
test_pack_kotek-0.0.1.dist-info/RECORD
