Metadata-Version: 2.1
Name: test-pack-kotek
Version: 0.0.1
Summary: PYPI TESTING!!
Author: kotvpalto
Author-email: kotvpaltoof@ya.ru
Classifier: Programming Language :: Python :: 3
Classifier: License :: OSI Approved :: MIT License
Classifier: Operating System :: OS Independent
Requires-Python: >=3.6
